{
  "version": "7",
  "dialect": "postgresql",
  "entries": [
    {
      "idx": 0,
      "version": "7",
      "when": 1776465354045,
      "tag": "0000_shallow_slayback",
      "breakpoints": true
    },
    {
      "idx": 1,
      "version": "7",
      "when": 1777386082096,
      "tag": "0001_messages_chats_refactor",
      "breakpoints": true
    },
    {
      "idx": 2,
      "version": "7",
      "when": 1777386917778,
      "tag": "0002_e2ee_message_chat_alignment",
      "breakpoints": true
    },
    {
      "idx": 3,
      "version": "7",
      "when": 1777406400000,
      "tag": "0003_encrypted_contacts",
      "breakpoints": true
    },
    {
      "idx": 4,
      "version": "7",
      "when": 1778000000000,
      "tag": "0004_group_chat_metadata",
      "breakpoints": true
    },
    {
      "idx": 5,
      "version": "7",
      "when": 1778000001000,
      "tag": "0005_group_member_admins",
      "breakpoints": true
    },
    {
      "idx": 6,
      "version": "7",
      "when": 1778112000000,
      "tag": "0006_chat_user_settings",
      "breakpoints": true
    },
    {
      "idx": 7,
      "version": "7",
      "when": 1778112001000,
      "tag": "0007_chat_user_setting_timestamps",
      "breakpoints": true
    }
  ]
}
